Workbook

Sheet RESUMO
A1: Apartamento Amadora
A2: Mapa de quantidades
A3: Resumo
B5: RESUMO: Total geral | C5: =C7+C10+C14+C20+C23+C27+C30 -> #REF!
A7: =#REF! -> #REF! | B7: =#REF! -> #REF! | C7: =SUM(C8:C8) -> #REF!
A8: =#REF! -> #REF! | B8: =#REF! -> #REF! | C8: =#REF! -> #REF!
A10: =#REF! -> #REF! | B10: =#REF! -> #REF! | C10: =SUM(C11:C13) -> #REF!
A11: =#REF! -> #REF! | B11: =#REF! -> #REF! | C11: =#REF! -> #REF!
A12: =#REF! -> #REF! | B12: =#REF! -> #REF! | C12: =#REF! -> #REF!
A14: =#REF! -> #REF! | B14: =#REF! -> #REF! | C14: =SUM(C15:C18) -> #REF!
A15: =#REF! -> #REF! | B15: =#REF! -> #REF! | C15: =#REF! -> #REF!
A16: =#REF! -> #REF! | B16: =#REF! -> #REF! | C16: =#REF! -> #REF!
A17: =#REF! -> #REF! | B17: =#REF! -> #REF! | C17: =#REF! -> #REF!
A18: =#REF! -> #REF! | B18: =#REF! -> #REF! | C18: =#REF! -> #REF!
A20: =#REF! -> #REF! | B20: =#REF! -> #REF! | C20: =SUM(C21) -> #REF!
A21: =#REF! -> #REF! | B21: =#REF! -> #REF! | C21: =#REF! -> #REF!
A23: =#REF! -> #REF! | B23: =#REF! -> #REF! | C23: =SUM(C24:C25) -> #REF!
A24: =#REF! -> #REF! | B24: =#REF! -> #REF! | C24: =#REF! -> #REF!
A25: =#REF! -> #REF! | B25: =#REF! -> #REF! | C25: =#REF! -> #REF!
A27: =#REF! -> #REF! | B27: =#REF! -> #REF! | C27: =SUM(C28) -> #REF!
A28: =#REF! -> #REF! | B28: =#REF! -> #REF! | C28: =#REF! -> #REF!
A30: =#REF! -> #REF! | B30: =#REF! -> #REF! | C30: =SUM(C31:C33) -> #REF!
A31: =#REF! -> #REF! | B31: =#REF! -> #REF! | C31: =#REF! -> #REF!
A32: =#REF! -> #REF! | B32: =#REF! -> #REF! | C32: =#REF! -> #REF!
A33: 7.3 | B33: =#REF! -> #REF! | C33: =#REF! -> #REF!
B37: Margem | C37: =Orçamento!#REF!+Orçamento!#REF!+Orçamento!#REF!+Orçamento!#REF!+Orçamento!#REF!+Orçamento!#REF!+Orçamento!#REF!+Orçamento!#REF!+Orçamento!#REF! -> #REF!

Sheet Orçamento
A1: =RESUMO!A1 -> Apartamento Amadora
A2: Mapa de quantidades
A3: Lista de artigos
E5: Preço do artigo | G5: Totais | I5: Observações
A6: Artigo | B6: Referência | C6: Qtd. | D6: un | E6: Unitário | F6: Total | G6: Parcial | H6: Capítulo
F7: =IF(D7=0,".",C7*E7) -> .
B8: NOTAS IMPORTANTES: | F8: =IF(D8=0,".",C8*E8) -> .
F9: =IF(D9=0,".",C9*E9) -> .
A10: 1 | B10: Os valores apresentados estão excluídos de IVA à taxa legal em vigor
A12: 1 | B12: Demolições e Apoio de Construção Civil | F12: =IF(D12=0,".",C12*E12) -> .
F13: =IF(D13=0,".",C13*E13) -> .
A14: 1.1 | B14: Demolições | F14: =IF(D14=0,".",C14*E14) -> .
F15: =IF(D15=0,".",C15*E15) -> .
A16: 1.1.1 | B16: Demolição, desmonte, transporte para vazadouro e reciclagem de parede entre casa de banho e quarto, parede entre sala e varanda; parede entre cozinha e varanda; parede de fora da cozinha. E os respectivos remates e todos os acabamento necessários para que estas superficios sejam pintadas. | C16: 1 | D16: vg | E16: 3000 | F16: =IF(D16=0,".",C16*E16) -> 3000
B19: Total | F19: =IF(D19=0,".",C19*E19) -> . | G19: =SUM(F$7:F19)-SUM(G$7:G17) -> 3000
A21: 1.2 | B21: Apoio de construção civil | F21: =IF(D21=0,".",C21*E21) -> .
F22: =IF(D22=0,".",C22*E22) -> .
A23: 1.2.1 | B23: Execução e remate dos roços necessários para a instalação da nova rede elétrica e de águas. Incluindo os equipamentos e materiais necessário para a correcta execução do trabalho. | C23: 1 | D23: vg | E23: 1100 | F23: =IF(D23=0,".",C23*E23) -> 1100
A25: 1.2.2 | B25: Execução de nova parede da IS e parede que tapa o vão existente entre a cozinha e o quarto, incluindo acabamento para ser pintada. | C25: 1 | D25: vg | E25: 1100 | F25: =IF(D25=0,".",C25*E25) -> 1100
B27: Total | F27: =IF(D27=0,".",C27*E27) -> . | G27: =SUM(F$7:F27)-SUM(G$7:G24) -> 2200
A30: TOTAL: | B30: =B12 -> Demolições e Apoio de Construção Civil | F30: =IF(D30=0,".",C30*E30) -> . | H30: =SUM(G$7:G30)-SUM(H$7:H29) -> 5200
F31: =IF(D31=0,".",C31*E31) -> .
A32: 2 | B32: Cozinha | F32: =IF(D32=0,".",C32*E32) -> .
A34: 2.2 | B34: Cerâmico | F34: =IF(D34=0,".",C34*E34) -> .
F35: =IF(D35=0,".",C35*E35) -> .
A36: 2.2.1 | B36: Aplicação de cerâmico no pavimento, incluindo todo o material necessário à sua correta aplicação: cimento cola, betume, espacadores, selantes e perfis de encaixe. Neste artigo o cerâmico está excluido. | C36: 1 | D36: vg | E36: 700 | F36: =IF(D36=0,".",C36*E36) -> 700
B38: Total | F38: =IF(D38=0,".",C38*E38) -> . | G38: =SUM(F$7:F38)-SUM(G$7:G37) -> 700
A41: TOTAL: | B41: =B32 -> Cozinha | F41: =IF(D41=0,".",C41*E41) -> . | H41: =SUM(G$7:G41)-SUM(H$7:H40) -> 700
A43: 3 | B43: Instalações Sanitárias | F43: =IF(D43=0,".",C43*E43) -> .
F44: =IF(D44=0,".",C44*E44) -> .
A45: 3.1 | B45: Cerâmico (IS social)
A47: 3.1.1 | B47: Aplicação de cerâmico nas paredes e pavimento, incluindo todo o material necessáiro à sua correta aplicação: cimento cola, betume, espacadores, selantes e perfis de encaixe. Neste artigo o cerâmico está excluido. | C47: 1 | D47: vg | E47: 800 | F47: =IF(D47=0,".",C47*E47) -> 800
F48: =IF(D48=0,".",C48*E48) -> .
B49: Total | F49: =IF(D49=0,".",C49*E49) -> . | G49: =SUM(F$7:F49)-SUM(G$7:G48) -> 800
A51: 3.2 | B51: Cerâmico (IS principal) | F51: =IF(D51=0,".",C51*E51) -> .
F52: =IF(D52=0,".",C52*E52) -> .
A53: 3.2.1 | B53: Aplicação de cerâmico nas paredes e pavimento, incluindo todo o material necessáiro à sua correta aplicação: cimento cola, betume, espacadores, selantes e perfis de encaixe. Neste artigo o cerâmico está excluido. | C53: 1 | D53: vg | E53: 1000 | F53: =IF(D53=0,".",C53*E53) -> 1000
B55: Total | F55: =IF(D55=0,".",C55*E55) -> . | G55: =SUM(F$7:F55)-SUM(G$7:G52) -> 1000
A58: 3.3 | B58: Instalação de equipamentos das IS | F58: =IF(D58=0,".",C58*E58) -> .
A60: 3.3.1 | B60: Instalação de equipamentos das IS | C60: 1 | D60: un | E60: 500 | F60: =IF(D60=0,".",C60*E60) -> 500
B62: Total | F62: =IF(D62=0,".",C62*E62) -> . | G62: =SUM(F$7:F62)-SUM(G$7:G60) -> 500
A64: TOTAL: | B64: =B43 -> Instalações Sanitárias | F64: =IF(D64=0,".",C64*E64) -> . | H64: =SUM(G$7:G64)-SUM(H$7:H63) -> 2300
A66: 4 | B66: Portas | F66: =IF(D66=0,".",C66*E66) -> .
F67: =IF(D67=0,".",C67*E67) -> .
A68: 4.1 | B68: Portas interiores | F68: =IF(D68=0,".",C68*E68) -> .
F69: =IF(D69=0,".",C69*E69) -> .
A70: 4.1.1 | B70: Aplicação e afinação de portas, aduelas e ombreiras bem como remate das paredes resultante da demolição das portas existentes. | C70: 1 | D70: vg | E70: 1200 | F70: =IF(D70=0,".",C70*E70) -> 1200
B72: Total | F72: =IF(D72=0,".",C72*E72) -> . | G72: =SUM(F$7:F72)-SUM(G$7:G71) -> 1200
F73: =IF(D73=0,".",C73*E73) -> .
F74: =IF(D74=0,".",C74*E74) -> .
A75: TOTAL: | B75: =B66 -> Portas | F75: =IF(D75=0,".",C75*E75) -> . | H75: =SUM(G$7:G75)-SUM(H$7:H74) -> 1200
A77: 5 | B77: Canalizações | F77: =IF(D77=0,".",C77*E77) -> .
F78: =IF(D78=0,".",C78*E78) -> .
A79: 5.1 | B79: Canalizações | F79: =IF(D79=0,".",C79*E79) -> .
F80: =IF(D80=0,".",C80*E80) -> .
A81: 5.1.1 | B81: Fornecimento e montagem de rede de distribuição de água e drenagem no interior do apartamento. Incluindo: tubagem, acessórios de ligação, torneiras de corte e sifões. | C81: 1 | D81: vg | E81: 2500 | F81: =IF(D81=0,".",C81*E81) -> 2500
B83: Total | F83: =IF(D83=0,".",C83*E83) -> . | G83: =SUM(F$7:F83)-SUM(G$7:G82) -> 2500
F84: =IF(D84=0,".",C84*E84) -> .
F85: =IF(D85=0,".",C85*E85) -> .
A86: TOTAL: | B86: =B77 -> Canalizações | F86: =IF(D86=0,".",C86*E86) -> . | H86: =SUM(G$7:G86)-SUM(H$7:H85) -> 2500
F87: =IF(D87=0,".",C87*E87) -> .
A88: 6 | B88: Eletricidade | F88: =IF(D88=0,".",C88*E88) -> .
F89: =IF(D89=0,".",C89*E89) -> .
A90: 6.1 | B90: Eletricidade | F90: =IF(D90=0,".",C90*E90) -> .
F91: =IF(D91=0,".",C91*E91) -> .
A92: 6.1.1 | B92: Fornecimento e montagem de quadro elétrico novo (Efapel): incluindo dijuntores, alteração, diferenciais de correr, cablagem elétrica de todo o apartamento e uniformização de aparelhagem. | C92: 1 | D92: vg | E92: 3000 | F92: =IF(D92=0,".",C92*E92) -> 3000
B94: Total | F94: =IF(D94=0,".",C94*E94) -> . | G94: =SUM(F$7:F94)-SUM(G$7:G93) -> 3000
F95: =IF(D95=0,".",C95*E95) -> .
F96: =IF(D96=0,".",C96*E96) -> .
A97: TOTAL: | B97: =B88 -> Eletricidade | F97: =IF(D97=0,".",C97*E97) -> . | H97: =SUM(G$7:G97)-SUM(H$7:H96) -> 3000
F98: =IF(D98=0,".",C98*E98) -> .
A99: 7 | B99: Pintura e pladur | F99: =IF(D99=0,".",C99*E99) -> .
F100: =IF(D100=0,".",C100*E100) -> .
A101: 7.1 | B101: Pintura e pladur | F101: =IF(D101=0,".",C101*E101) -> .
F102: =IF(D102=0,".",C102*E102) -> .
A103: 7.1.1 | B103: Reparação e regularização de paredes | C103: 1 | D103: vg | E103: 800 | F103: =IF(D103=0,".",C103*E103) -> 800
A105: 7.1.1 | B105: Reparação e pintura geral de paredes e tetos à cor branca, incluindo primário e 3 demãos de pintura. | C105: 1 | D105: vg | E105: 1400 | F105: =IF(D105=0,".",C105*E105) -> 1400
A107: 7.1.2 | B107: Fornecimento e a plicação de pladur no teto do hall (incl. alhetas), corredor (incl. alhetas), cozinha (incl. sancas) e casas de banho (incl. sancas) | C107: 1 | D107: vg | E107: 1000 | F107: =IF(D107=0,".",C107*E107) -> 1000
B109: Total | F109: =IF(D109=0,".",C109*E109) -> . | G109: =SUM(F$7:F109)-SUM(G$7:G108) -> 3200
F110: =IF(D110=0,".",C110*E110) -> .
F111: =IF(D111=0,".",C111*E111) -> .
A112: TOTAL: | B112: =B99 -> Pintura e pladur | F112: =IF(D112=0,".",C112*E112) -> . | H112: =SUM(G$7:G112)-SUM(H$7:H111) -> 3200
F113: =IF(D113=0,".",C113*E113) -> .
A114: 9 | B114: Pavimento | F114: =IF(D114=0,".",C114*E114) -> .
F115: =IF(D115=0,".",C115*E115) -> .
A116: 9.1 | B116: Pavimento | F116: =IF(D116=0,".",C116*E116) -> .
F117: =IF(D117=0,".",C117*E117) -> .
A118: 9.1.1 | B118: Regularização do pavimento (se necessário arrancar soalho e regularizar) | C118: 1 | D118: vg | E118: 1300 | F118: =IF(D118=0,".",C118*E118) -> 1300
A120: 9.1.2 | B120: Aplicação de vinilico no hall,corredor, sala e quartos | C120: 1 | D120: vg | E120: 1400 | F120: =IF(D120=0,".",C120*E120) -> 1400
B122: Total | F122: =IF(D122=0,".",C122*E122) -> . | G122: =SUM(F$7:F122)-SUM(G$7:G120) -> 2700
F123: =IF(D123=0,".",C123*E123) -> .
A124: TOTAL: | B124: =B114 -> Pavimento | F124: =IF(D124=0,".",C124*E124) -> . | H124: =SUM(G$7:G124)-SUM(H$7:H123) -> 2700
F125: =IF(D125=0,".",C125*E125) -> .
A126: 10 | B126: Logistica | F126: =IF(D126=0,".",C126*E126) -> .
F127: =IF(D127=0,".",C127*E127) -> .
A128: 10.1 | B128: Logistica | F128: =IF(D128=0,".",C128*E128) -> .
F129: =IF(D129=0,".",C129*E129) -> .
A130: 10.1.1 | B130: Serviço de ir levantar à loja e transportar para o apartamento os seguintes materiais: ceramico, pavimento, rodapés, moveis de casa de banho, sanitários, torneiras, eletrodoméstico, guardar de duche | C130: 1 | D130: un | E130: 1200 | F130: =IF(D130=0,".",C130*E130) -> 1200 | I130: Este valor está exagerado, mas não sei onde colocar mais dinheiro de forma a fazer os 22k€.
B132: Total | F132: =IF(D132=0,".",C132*E132) -> . | G132: =SUM(F$7:F132)-SUM(G$7:G129) -> 1200
F134: =IF(D134=0,".",C134*E134) -> .
...

Sheet medição
A1: =RESUMO!A1 -> Apartamento Amadora
A2: Mapa de quantidades
A3: Medições
A5: Artigo | B5: Referência | C5: P. iguais | D5: Comp. | E5: Larg. | F5: Altura | G5: Element. | H5: Parciais | I5: Totais
G6: =IF(C6=0,"",PRODUCT(C6:F6))
A7: 3.1.2 | B7: Área de cerâmico a arrancar | C7: 1 | D7: 8.5 | F7: 1.6 | G7: =IF(C7=0,".",PRODUCT(C7:F7)) -> 13.6
G9: =IF(C9=0,".",PRODUCT(C9:F9)) -> . | H9: =SUM(G7:G8) -> 13.6
G10: =IF(C10=0,".",PRODUCT(C10:F10)) -> .
G11: =IF(C11=0,".",PRODUCT(C11:F11)) -> .
B12: Fornecimento de cerâmico para paredes da instalação sanitária. | C12: 1 | D12: 8.5 | F12: 2.5 | G12: =IF(C12=0,".",PRODUCT(C12:F12)) -> 21.25
G13: =IF(C13=0,".",PRODUCT(C13:F13)) -> .
G14: =IF(C14=0,".",PRODUCT(C14:F14)) -> . | H14: =SUM(G12:G13) -> 21.25
G15: =IF(C15=0,".",PRODUCT(C15:F15)) -> .
B16: Fornecimento de cerâmico para pavimento da instlaação sanitária. | C16: 1.1 | D16: 1.18 | E16: 0.73 | G16: =IF(C16=0,".",PRODUCT(C16:F16)) -> 0.94754
C17: 1.1 | D17: 2.1 | E17: 1.1 | G17: =IF(C17=0,".",PRODUCT(C17:F17)) -> 2.541
C18: 1.1 | D18: 0.8 | E18: 0.22 | G18: =IF(C18=0,".",PRODUCT(C18:F18)) -> 0.242
C19: 1.1 | D19: 0.91 | E19: 0.72 | G19: =IF(C19=0,".",PRODUCT(C19:F19)) -> 1.001
G20: =IF(C20=0,".",PRODUCT(C20:F20)) -> . | H20: =SUM(G16:G19) -> 4.73154
G21: =IF(C21=0,".",PRODUCT(C21:F21)) -> .
G22: =IF(C22=0,".",PRODUCT(C22:F22)) -> .
G23: =IF(C23=0,".",PRODUCT(C23:F23)) -> .
G24: =IF(C24=0,".",PRODUCT(C24:F24)) -> .
G25: =IF(C25=0,".",PRODUCT(C25:F25)) -> .
G26: =IF(C26=0,".",PRODUCT(C26:F26)) -> .
G27: =IF(C27=0,".",PRODUCT(C27:F27)) -> .
G28: =IF(C28=0,".",PRODUCT(C28:F28)) -> .
G29: =IF(C29=0,".",PRODUCT(C29:F29)) -> .
G30: =IF(C30=0,".",PRODUCT(C30:F30)) -> .
G31: =IF(C31=0,".",PRODUCT(C31:F31)) -> .
G32: =IF(C32=0,".",PRODUCT(C32:F32)) -> .
... G85: =IF(C85=0,".",PRODUCT(C85:F85)) -> .

Sheet verificações
A1: =RESUMO!A1 -> Apartamento Amadora
A2: =RESUMO!A2 -> Mapa de quantidades
A3: Folha de verificação de somatórios
A5: ESTA FOLHA NÃO PRECISA DE SER IMPRESSA NEM ANEXA À PROPOSTA
C7: SOMA | D7: SOMA - D
A9: A | B9: Total global da folha resumo | C9: =RESUMO!C5 -> #REF! | D9: =C9-C$15 -> #REF!
A10: B | B10: Somatório de todos os totais e capítulos da folha resumo dividido por 2 | C10: =SUM(RESUMO!C6:C34)/2 -> #REF! | D10: =C10-C$15 -> #REF!
A11: C | B11: Total global da folha MQT - Parcelares (coluna G) | C11: =#REF! -> #REF! | D11: =C11-C$15 -> #REF!
A12: D | B12: Total global da folha MQT - Capítulos (coluna H) | C12: =#REF! -> #REF! | D12: =C12-C$15 -> #REF!
A15: E | B15: Somatório de todos os artigos do MQT | C15: =#REF! -> #REF!
